dadosic
