Metadata-Version: 2.4
Name: dadosic-zenlenium
Version: 0.1.2
Summary: Automação do zendesk com selenium e zenpy
Author: Gustavo Sartorio
Author-email: strov3rl@gmail.com
License: MIT License
Keywords: zendesk selenium
License-File: LICENCE
Requires-Dist: selenium
Requires-Dist: zenpy
Requires-Dist: requests
Requires-Dist: urllib3
Requires-Dist: python-dotenv
Requires-Dist: pandas
Requires-Dist: pandas-gbq
Requires-Dist: google-auth
Dynamic: author
Dynamic: author-email
Dynamic: description
Dynamic: description-content-type
Dynamic: keywords
Dynamic: license
Dynamic: license-file
Dynamic: requires-dist
Dynamic: summary
